clipkg/CLI.py
clipkg/__init__.py
clipkg/joke.py
clipkg/data/joke_for_test.txt
clipkg/data/profanities.txt
clipkg/data/profanity2_for_test.txt
clipkg/data/reddit_dadjokes.csv
pcl2_joke_cui-0.0.2.dist-info/LICENSE.txt
pcl2_joke_cui-0.0.2.dist-info/METADATA
pcl2_joke_cui-0.0.2.dist-info/WHEEL
pcl2_joke_cui-0.0.2.dist-info/top_level.txt
pcl2_joke_cui-0.0.2.dist-info/RECORD
