Metadata-Version: 2.1
Name: pcl2-joke-cui
Version: 0.0.2
Summary: creating CLI for processing joke.
Author: cui
Author-email: cui.ding@uzh.com
License: MIT
Platform: UNKNOWN
Classifier: Programming Language :: Python :: 3
Classifier: License :: OSI Approved :: MIT License
Classifier: Operating System :: OS Independent
Requires-Python: >=3.6
License-File: LICENSE.txt
